{"Acinetobacter_MS_1":{"name":"Acinetobacter_MS_1","id":0,"data":"Human GIT","regulation":0},
"Bordetella_1":{"name":"Bordetella_1","id":1,"data":"Fresh water","regulation":"Harmony"},
"Brevundimonas_MS_2":{"name":"Brevundimonas_MS_2","id":2,"data":"Fresh water","regulation":"Harmony"},
"Burkholderiales_MS_1":{"name":"Burkholderiales_MS_1","id":3,"data":"Fresh water","regulation":"Harmony"},
"Comamonadaceae_MS_12":{"name":"Comamonadaceae_MS_12","id":4,"data":"Fresh water","regulation":"Harmony"},
"Helicobacter_typhlonius_1":{"name":"Helicobacter_typhlonius_1","id":5,"data":"Mouse","regulation":"Harmony"},
"Noviherbaspirillum_MS_1":{"name":"Noviherbaspirillum_MS_1","id":6,"data":"Human GIT","regulation":"Harmony"},
"Polynucleobacter_duraquae_1":{"name":"Polynucleobacter_duraquae_1","id":7,"data":"Fresh water","regulation":"Harmony"},
"Rhodoferax_MS_1":{"name":"Rhodoferax_MS_1","id":8,"data":"Fresh water","regulation":"Harmony"},
"Bifidobacterium_MS_5":{"name":"Bifidobacterium_MS_5","id":9,"data":"Human GIT","regulation":"Harmony"},
"Clostridiales_MS_1":{"name":"Clostridiales_MS_1","id":10,"data":"Human GIT","regulation":"Harmony"},
"Clostridiales_MS_36":{"name":"Clostridiales_MS_36","id":11,"data":"Human GIT","regulation":"Harmony"},
"Clostridium_5":{"name":"Clostridium_5","id":12,"data":"Human GIT","regulation":"Harmony"},
"Finegoldia_magna_1":{"name":"Finegoldia_magna_1","id":13,"data":"Human GIT","regulation":"Harmony"},
"Gemmiger_formicilis_1":{"name":"Gemmiger_formicilis_1","id":14,"data":"Human GIT","regulation":"Harmony"},
"Lachnoclostridium_1":{"name":"Lachnoclostridium_1","id":15,"data":"Human GIT","regulation":"Harmony"},
"Lachnospiraceae_MS_2":{"name":"Lachnospiraceae_MS_2","id":16,"data":"Human GIT","regulation":"Harmony"},
"Lactobacillus_4":{"name":"Lactobacillus_4","id":17,"data":"Mouse","regulation":"Harmony"},
"Lactobacillus_7":{"name":"Lactobacillus_7","id":18,"data":"Mouse","regulation":"Harmony"},
"Lactobacillus_florum_1":{"name":"Lactobacillus_florum_1","id":19,"data":"Flower","regulation":"Destiny"},
"Levyella_massiliensis_1":{"name":"Levyella_massiliensis_1","id":20,"data":"Human GIT","regulation":"Destiny"},
"Roseburia_1":{"name":"Roseburia_1","id":21,"data":"Human GIT","regulation":"Destiny"},
"Ruminiclostridium_leptum_1":{"name":"Ruminiclostridium_leptum_1","id":22,"data":"Human GIT","regulation":"Harmony"},
"Ruminococcaceae_MS_6":{"name":"Ruminococcaceae_MS_6","id":23,"data":"Human GIT","regulation":"Harmony"},
"Subdoligranulum_1":{"name":"Subdoligranulum_1","id":24,"data":"Human GIT","regulation":"Harmony"},
"Bacteroidales_MS_7":{"name":"Bacteroidales_MS_7","id":25,"data":"Mouse","regulation":"Harmony"},
"Bacteroides_21":{"name":"Bacteroides_21","id":26,"data":"Human GIT","regulation":"Harmony"},
"Bacteroides_stercoris_2":{"name":"Bacteroides_stercoris_2","id":27,"data":"Human GIT","regulation":"Harmony"},
"Bacteroidetes_MS_4":{"name":"Bacteroidetes_MS_4","id":28,"data":"Fresh water","regulation":"Harmony"},
"Porphyromonas_4":{"name":"Porphyromonas_4","id":29,"data":"Human GIT","regulation":"Harmony"},
"Cryptomonadaceae_12":{"name":"Cryptomonadaceae_12","id":30,"data":"Fresh water","regulation":"Harmony"},
"TrueUnknown_151":{"name":"TrueUnknown_151","id":31,"data":"Human GIT","regulation":"Harmony"},
"TrueUnknown_16776":{"name":"TrueUnknown_16776","id":32,"data":"Human GIT","regulation":"Harmony"},
"Unknown_bacteria_56":{"name":"Unknown_bacteria_56","id":33,"data":"Mouse","regulation":"Harmony"},
"Human GIT":{"name":"Human GIT","id":34,"data":"reference","regulation":"Harmony"},
"Flower":{"name":"Flower","id":35,"data":"reference","regulation":"Harmony"},
"Fresh water":{"name":"Fresh water","id":36,"data":"reference","regulation":"Harmony"},
"Mouse":{"name":"Mouse","id":37,"data":"reference"}}
